setup.py
ajson_rpc2/__init__.py
ajson_rpc2/container.py
ajson_rpc2/method.py
ajson_rpc2/module.py
ajson_rpc2/server.py
ajson_rpc2/typedef.py
ajson_rpc2/utils.py
ajson_rpc2.egg-info/PKG-INFO
ajson_rpc2.egg-info/SOURCES.txt
ajson_rpc2.egg-info/dependency_links.txt
ajson_rpc2.egg-info/top_level.txt
ajson_rpc2/models/__init__.py
ajson_rpc2/models/batch_request.py
ajson_rpc2/models/batch_response.py
ajson_rpc2/models/errors.py
ajson_rpc2/models/fixed_list.py
ajson_rpc2/models/request.py
ajson_rpc2/models/response.py