Metadata-Version: 1.1
Name: ajson-rpc2
Version: 0.5
Summary: json rpc 2.0 implementations based on python3 asyncio module
Home-page: https://github.com/WindSoilder/ajson-rpc2
Author: WindSoilder
Author-email: WindSoilder@outlook.com
License: MIT
Keywords: rpc,json,server
Platform: UNKNOWN
Classifier: Development Status :: 5 - Production/Stable
Classifier: Intended Audience :: Developers
Classifier: Programming Language :: Python :: 3.6
Classifier: Topic :: Documentation
